extractlinks.py
extractlinks-0.1.0.dist-info/LICENSE
extractlinks-0.1.0.dist-info/METADATA
extractlinks-0.1.0.dist-info/WHEEL
extractlinks-0.1.0.dist-info/top_level.txt
extractlinks-0.1.0.dist-info/RECORD
