Metadata-Version: 2.1
Name: extractlinks
Version: 0.1.0
Summary: extract and repair links from Requests objects, including redirects and final landing page
Home-page: https://github.com/bonifield/extractlinks
Author: James Bonifield
Author-email: bonifield.tools@gmail.com
License: UNKNOWN
Platform: UNKNOWN
Classifier: Programming Language :: Python :: 3
Classifier: License :: OSI Approved :: MIT License
Classifier: Operating System :: OS Independent
License-File: LICENSE
